<?xml version="1.0" encoding="UTF-8" ?>
<Form>
  <FormId>sec_rep_itg</FormId>
  <PrototypeId>PaperNtFormSec</PrototypeId>
  <EntityName>форма НТ-СБ-ОТЧ</EntityName>
  <PhotocopierTitle>Отчёт о расследовании</PhotocopierTitle>
  <Content><![CDATA[[bold]Форма НТ-СБ-ОТЧ[/bold]
[head=2]Отчет о расследовании[/head]

[italic]Дата: %дата [/italic]

Я, %имя, в должности детектива провел расследование о деле (УКАЗАТЬ ДЕЛО).

[bold]Мною были допрошены свидетели:[/bold]

[bold]Проведены следующие оперативно-розыскные мероприятия:[/bold]

[bold]Взяты и приложены к делу следующие следы преступления:[/bold]

[bold]В ходе расследования доказано:[/bold]

[bold]Расследование прекращено по причине:[/bold]

Время: %время

[italic]Место для печатей – Детектив[/italic]]]></Content>
</Form>